cactool/__init__.py
cactool/__main__.py
cactool/database.py
cactool/dates.py
cactool/types.py
cactool/defaults/config.json
cactool/migrations/README
cactool/migrations/alembic.ini
cactool/migrations/env.py
cactool/migrations/script.py.mako
cactool/migrations/__pycache__/env.cpython-310.pyc
cactool/migrations/__pycache__/env.cpython-311.pyc
cactool/migrations/versions/07c0c9849f18_store_user_otp_secret.py
cactool/migrations/versions/07d73859b99c_add_show_data_type.py
cactool/migrations/versions/16942fdb0f18_add_relative_column_priorities.py
cactool/migrations/versions/19d06323ddd6_store_dataset_access_ranes.py
cactool/migrations/versions/28e8811a530d_support_dataset_file_storage.py
cactool/migrations/versions/51ed49d3ed75_support_user_email_verification.py
cactool/migrations/versions/5e7f3be664d5_rename_priority_column_to_order.py
cactool/migrations/versions/6286ef6698f9_merge_heads.py
cactool/migrations/versions/7226d855d8ec_add_more_ordinal_data_types.py
cactool/migrations/versions/c12d86b089b8_store_user_emails.py
cactool/migrations/versions/ce5fc447a2e8_add_image_display_type.py
cactool/migrations/versions/d1b66364eeb3_initial_migration.py
cactool/migrations/versions/__pycache__/072331977abf_store_user_emails.cpython-310.pyc
cactool/migrations/versions/__pycache__/07c0c9849f18_store_user_otp_secret.cpython-310.pyc
cactool/migrations/versions/__pycache__/07c0c9849f18_store_user_otp_secret.cpython-311.pyc
cactool/migrations/versions/__pycache__/07d73859b99c_add_show_data_type.cpython-310.pyc
cactool/migrations/versions/__pycache__/07d73859b99c_add_show_data_type.cpython-311.pyc
cactool/migrations/versions/__pycache__/0f3a32ab3b24_support_dataset_files.cpython-310.pyc
cactool/migrations/versions/__pycache__/16942fdb0f18_.cpython-310.pyc
cactool/migrations/versions/__pycache__/16942fdb0f18_add_relative_column_priorities.cpython-310.pyc
cactool/migrations/versions/__pycache__/16942fdb0f18_add_relative_column_priorities.cpython-311.pyc
Cactool-0.6.2.dist-info/LICENSE
Cactool-0.6.2.dist-info/METADATA
Cactool-0.6.2.dist-info/WHEEL
Cactool-0.6.2.dist-info/entry_points.txt
Cactool-0.6.2.dist-info/top_level.txt
Cactool-0.6.2.dist-info/RECORD
