Metadata-Version: 2.1
Name: Cactool
Version: 0.6.2
Summary: An easy way to collaboratively code social media posts for manual content and discourse analysis
Home-page: https://cactool.github.io
Author: Sam Ezeh
Author-email: sam.z.ezeh@gmail.com
Project-URL: Bug Tracker, https://github.com/cactool/cactool/issues
Classifier: Programming Language :: Python :: 3
Classifier: License :: OSI Approved :: MIT License
Classifier: Operating System :: OS Independent
Requires-Python: >=3.6
License-File: LICENSE
Requires-Dist: requests
Requires-Dist: Flask
Requires-Dist: Flask-Login
Requires-Dist: Flask-SQLAlchemy
Requires-Dist: passlib (>=1.7)
Requires-Dist: Werkzeug
Requires-Dist: waitress
Requires-Dist: Flask-Migrate
Requires-Dist: cryptography (>=36)
Requires-Dist: appdirs
Requires-Dist: pyotp
Requires-Dist: qrcode
Requires-Dist: beautifulsoup4
